{
  "pack_id": "2da1817c-a436-4996-a715-647ef75ccaa5",
  "created_at": "2026-02-26T13:54:40.919479+00:00",
  "workspace_dir": "/Users/axient/repository/AxiomMe",
  "passed": true,
  "status": "pass",
  "unresolved_blockers": 0,
  "decisions": [
    {
      "gate_id": "G0",
      "passed": true,
      "status": "pass",
      "details": {
        "kind": "contract_integrity",
        "data": {
          "policy": {
            "required_major": 0,
            "required_minor": 1,
            "required_lock_source_prefix": "registry+https://github.com/rust-lang/crates.io-index",
            "allowed_manifest_operators": [
              "exact",
              "caret",
              "tilde"
            ]
          },
          "contract_probe": {
            "test_name": "client::tests::relation_trace_logs::contract_execution_probe_validates_core_algorithms",
            "command_ok": true,
            "matched": true,
            "output_excerpt": "\nrunning 1 test\ntest client::tests::relation_trace_logs::contract_execution_probe_validates_core_algorithms ... ok\n\ntest result: ok. 1 passed; 0 failed; 0 ignored; 0 measured; 588 filtered out; finish...",
            "passed": true
          },
          "episodic_api_probe": {
            "test_name": "client::tests::relation_trace_logs::episodic_api_probe_validates_om_contract",
            "command_ok": true,
            "matched": true,
            "output_excerpt": "\nrunning 1 test\ntest client::tests::relation_trace_logs::episodic_api_probe_validates_om_contract ... ok\n\ntest result: ok. 1 passed; 0 failed; 0 ignored; 0 measured; 588 filtered out; finished in 0.00...",
            "passed": true
          },
          "episodic_semver_probe": {
            "passed": true,
            "error": null,
            "manifest_req": "0.1.0",
            "manifest_req_ok": true,
            "manifest_uses_path": false,
            "manifest_uses_git": false,
            "manifest_source_ok": true,
            "lock_version": "0.1.0",
            "lock_version_ok": true,
            "lock_source": "registry+https://github.com/rust-lang/crates.io-index",
            "lock_source_ok": true
          },
          "ontology_policy": {
            "schema_uri": "axiom://agent/ontology/schema.v1.json",
            "required_schema_version": 1,
            "probe_test_name": "ontology::validate::tests::ontology_contract_probe_default_schema_is_compilable"
          },
          "ontology_probe": {
            "passed": true,
            "error": null,
            "command_probe": {
              "test_name": "ontology::validate::tests::ontology_contract_probe_default_schema_is_compilable",
              "command_ok": true,
              "matched": true,
              "output_excerpt": "\nrunning 1 test\ntest ontology::validate::tests::ontology_contract_probe_default_schema_is_compilable ... ok\n\ntest result: ok. 1 passed; 0 failed; 0 ignored; 0 measured; 588 filtered out; finished in 0...",
              "passed": true
            },
            "schema": {
              "schema_uri": "axiom://agent/ontology/schema.v1.json",
              "schema_version": 1,
              "schema_version_ok": true
            },
            "cardinality": {
              "object_type_count": 0,
              "link_type_count": 0,
              "action_type_count": 0,
              "invariant_count": 0
            },
            "invariant_checks": {
              "passed": 0,
              "failed": 0
            }
          }
        }
      }
    },
    {
      "gate_id": "G1",
      "passed": true,
      "status": "pass",
      "details": {
        "kind": "build_quality",
        "data": {
          "cargo_check": true,
          "cargo_fmt": true,
          "cargo_clippy": true,
          "check_output": "    Checking axiomme-core v0.1.1 (/Users/axient/repository/AxiomMe/crates/axiomme-core)\n    Checking axiomme-mobile-ffi v0.1.1 (/Users/axient/repository/AxiomMe/crates/axiomme-mobile-ffi)\n    Checking axiomme-cli v0.1.1 (/Users/axient/repos...",
          "fmt_output": "",
          "clippy_output": "    Finished `dev` profile [unoptimized + debuginfo] target(s) in 0.14s\n"
        }
      }
    },
    {
      "gate_id": "G2",
      "passed": true,
      "status": "pass",
      "details": {
        "kind": "reliability_evidence",
        "data": {
          "status": "pass",
          "replay_done": 1,
          "dead_letter": 0
        }
      },
      "evidence_uri": "axiom://queue/release/reliability/3a715320-208e-4d94-bd45-a3d1928ab301.json"
    },
    {
      "gate_id": "G3",
      "passed": true,
      "status": "pass",
      "details": {
        "kind": "eval_quality",
        "data": {
          "executed_cases": 2,
          "top1_accuracy": 1.0,
          "min_top1_accuracy": 0.75,
          "failed": 0,
          "filter_ignored": 0,
          "relation_missing": 0
        }
      },
      "evidence_uri": "axiom://queue/eval/reports/f7ab5b5a-b5bc-4edd-b5b6-e4dbe59cadd0.json"
    },
    {
      "gate_id": "G4",
      "passed": true,
      "status": "pass",
      "details": {
        "kind": "session_memory",
        "data": {
          "base_details": "session_id=release-gate-dd3760ff171141bb8f01a09415de3cf0 memories_extracted=9 hit_count=1 missing_categories=-",
          "memory_category_miss": 0
        }
      }
    },
    {
      "gate_id": "G5",
      "passed": true,
      "status": "pass",
      "details": {
        "kind": "security_audit",
        "data": {
          "status": "pass",
          "mode": "strict",
          "strict_mode_required": true,
          "strict_mode": true,
          "audit_status": "passed",
          "advisories_found": 0,
          "packages": 278
        }
      },
      "evidence_uri": "axiom://queue/release/security/9b2967f5-e2d9-4e59-8798-040ace49a4ad.json"
    },
    {
      "gate_id": "G6",
      "passed": true,
      "status": "pass",
      "details": {
        "kind": "benchmark",
        "data": {
          "passed": true,
          "evaluated_runs": 1,
          "passing_runs": 1,
          "reasons": [
            "ok"
          ]
        }
      },
      "evidence_uri": "axiom://queue/release/gates/011e452f-ce31-40ce-85ea-05b0d4f72482.json"
    },
    {
      "gate_id": "G7",
      "passed": true,
      "status": "pass",
      "details": {
        "kind": "operability_evidence",
        "data": {
          "status": "pass",
          "traces_analyzed": 3,
          "request_logs_scanned": 12
        }
      },
      "evidence_uri": "axiom://queue/release/operability/ccada1fe-f0b5-4aeb-9c48-c668c7580d5b.json"
    },
    {
      "gate_id": "G8",
      "passed": true,
      "status": "pass",
      "details": {
        "kind": "blocker_rollup",
        "data": {
          "unresolved_blockers": 0
        }
      }
    }
  ],
  "report_uri": "axiom://queue/release/packs/2da1817c-a436-4996-a715-647ef75ccaa5.json"
}
